explicit/django/__init__.py
explicit/django/py.typed
explicit/django/unit_of_work.py
explicit/django/domain/__init__.py
explicit/django/domain/validation/__init__.py
explicit/django/domain/validation/exceptions.py
explicit_python_django-1.1.0.dist-info/METADATA
explicit_python_django-1.1.0.dist-info/WHEEL
explicit_python_django-1.1.0.dist-info/dependency_links.txt
explicit_python_django-1.1.0.dist-info/top_level.txt
explicit_python_django-1.1.0.dist-info/RECORD
